langfuse_web/__init__.py
langfuse_web/langfuse_web.py
langfuse_web-0.0.6.dist-info/METADATA
langfuse_web-0.0.6.dist-info/WHEEL
langfuse_web-0.0.6.dist-info/RECORD
