Metadata-Version: 2.1
Name: langfuse_web
Version: 0.0.6
Summary: Support for Langfuse operations not handed in the API library
Home-page: https://github.com/invisiblethreat/langfuse_web
Keywords: langfuse,prompts
Author: Scott Walsh
Author-email: scott@invisiblethreat.ca
Requires-Python: >=3.8
Classifier: Development Status :: 4 - Beta
Classifier: Programming Language :: Python
Classifier: Programming Language :: Python :: 3
Classifier: Programming Language :: Python :: 3.8
Classifier: Programming Language :: Python :: 3.9
Classifier: Programming Language :: Python :: 3.10
Classifier: Programming Language :: Python :: 3.11
Classifier: Programming Language :: Python :: 3.12
Requires-Dist: pyredacter (>=0.0.3,<0.0.4)
Requires-Dist: requests (>=2.31.0,<3.0.0)
Project-URL: Documentation, https://github.com/invisiblethreat/langfuse_web/blob/main/README.md
Project-URL: Repository, https://github.com/invisiblethreat/langfuse_web
